README.md
setup.py
path_tree.egg-info/PKG-INFO
path_tree.egg-info/SOURCES.txt
path_tree.egg-info/dependency_links.txt
path_tree.egg-info/not-zip-safe
path_tree.egg-info/requires.txt
path_tree.egg-info/top_level.txt
pathtree/__init__.py
pathtree/path.py
pathtree/tempfile.py