Metadata-Version: 2.1
Name: path-tree
Version: 0.0.15
Summary: Define named directory structure using placeholders
Home-page: https://github.com/beasteers/pathtree
Author: Bea Steers
Author-email: bea.steers@gmail.com
License: MIT License
Keywords: path directory tree structure partial format
Platform: UNKNOWN
